sideload_loki_main_bin_67182bd5ad19ca34f8bcee10/__init__.py
sideload_loki_main_bin_67182bd5ad19ca34f8bcee10/loki-main.zip
sideload_loki_main_bin_67182bd5ad19ca34f8bcee10-1.0.0.dist-info/METADATA
sideload_loki_main_bin_67182bd5ad19ca34f8bcee10-1.0.0.dist-info/WHEEL
sideload_loki_main_bin_67182bd5ad19ca34f8bcee10-1.0.0.dist-info/top_level.txt
sideload_loki_main_bin_67182bd5ad19ca34f8bcee10-1.0.0.dist-info/RECORD
