Metadata-Version: 2.1
Name: sideload_loki_main_bin_67182bd5ad19ca34f8bcee10
Version: 1.0.0
Summary: Sideloaded package
Author: Null Void
Requires-Python: >=3.8
